sfu_api/__init__.py
sfu_api/models.py
sfu_api/py.typed
sfu_api-0.1.5.dist-info/METADATA
sfu_api-0.1.5.dist-info/WHEEL
sfu_api-0.1.5.dist-info/licenses/LICENSE
sfu_api-0.1.5.dist-info/RECORD
